{
  "parent": "minecraft:recipes/root",
  "rewards": {
    "recipes": [
      "fantasy_trees:fantasy_spruce_planks"
    ]
  },
  "criteria": {
    "has_spruce_log": {
      "trigger": "minecraft:inventory_changed",
      "conditions": {
        "items": [
          {
            "items": [
              "fantasy_trees:fantasy_spruce_log"
            ]
          }
        ]
      }
    },
    "has_the_recipe": {
      "trigger": "minecraft:recipe_unlocked",
      "conditions": {
        "recipe": "fantasy_trees:fantasy_spruce_planks"
      }
    }
  },
  "requirements": [
    [
      "has_spruce_log",
      "has_the_recipe"
    ]
  ]
}